entrophier/__init__.py
entrophier/__main__.py
entrophier/cli.py
entrophier/common_words.yaml
entrophier/config.py
entrophier/core.py
entrophier/entropy_settings.yaml
entrophier/redaction_patterns.yaml
entrophier-0.1.0.dist-info/METADATA
entrophier-0.1.0.dist-info/WHEEL
entrophier-0.1.0.dist-info/entry_points.txt
entrophier-0.1.0.dist-info/licenses/LICENSE
entrophier-0.1.0.dist-info/RECORD
