Metadata-Version: 2.4
Name: entrophier
Version: 0.1.0
Summary: A configurable Python tool for detecting and redacting sensitive data using entropy analysis and pattern matching
Project-URL: Repository, https://github.com/rjury-sumo/python-entrophier
Project-URL: Documentation, https://github.com/rjury-sumo/python-entrophier#readme
Project-URL: Bug Tracker, https://github.com/rjury-sumo/python-entrophier/issues
Project-URL: Changelog, https://github.com/rjury-sumo/python-entrophier/blob/main/CHANGELOG.md
Author-email: Python Entrophier Contributors <noreply@example.com>
License-File: LICENSE
Keywords: data-sanitization,entropy,log-sanitization,pii,privacy,redaction,security
Classifier: Development Status :: 4 - Beta
Classifier: Intended Audience :: Developers
Classifier: Intended Audience :: System Administrators
Classifier: License :: OSI Approved :: MIT License
Classifier: Operating System :: OS Independent
Classifier: Programming Language :: Python :: 3
Classifier: Programming Language :: Python :: 3.8
Classifier: Programming Language :: Python :: 3.9
Classifier: Programming Language :: Python :: 3.10
Classifier: Programming Language :: Python :: 3.11
Classifier: Programming Language :: Python :: 3.12
Classifier: Programming Language :: Python :: 3.13
Classifier: Topic :: Security
Classifier: Topic :: Text Processing
Classifier: Topic :: Text Processing :: Filters
Requires-Python: >=3.8
Requires-Dist: pyyaml>=6.0.0
